{
  "resourceType": "Observation",
  "id": "head-circumference",
  "meta": {
    "profile": [
      "http://hl7.org.au/fhir/argonaut/StructureDefinition/argo-vitalsigns"
    ]
  },
  "status": "final",
  "category": [
    {
      "coding": [
        {
          "system": "http://hl7.org/fhir/observation-category",
          "code": "vital-signs",
          "display": "Vital Signs",
          "userSelected": false
        }
      ],
      "text": "Vital Signs"
    }
  ],
  "code": {
    "coding": [
      {
        "system": "http://loinc.org",
        "code": "8287-5",
        "display": "head_circumference",
        "userSelected": false
      }
    ],
    "text": "head_circumference"
  },
  "subject": {
    "reference": "Patient/peter-chalmers"
  },
  "context": {
    "reference": "Encounter/691"
  },
  "effectiveDateTime": "2010-08-12",
  "valueQuantity": {
    "value": 51.2,
    "unit": "cm",
    "system": "http://unitsofmeasure.org",
    "code": "cm"
  }
}